django_filters_mixin-0.1.4.dist-info/DESCRIPTION.rst
django_filters_mixin-0.1.4.dist-info/METADATA
django_filters_mixin-0.1.4.dist-info/RECORD
django_filters_mixin-0.1.4.dist-info/WHEEL
django_filters_mixin-0.1.4.dist-info/metadata.json
django_filters_mixin-0.1.4.dist-info/top_level.txt
filters/__init__.py
filters/models.py
filters/views.py
